{
  "slug": "agregacoes",
  "titulo": "Funções de Agregação",
  "descricao": "Conte registros, some valores, calcule médias e encontre mínimos e máximos com COUNT, SUM, AVG, MIN e MAX.",
  "icone": "📈",
  "ordem": 6,
  "xpTotal": 1450,
  "traducoes": {
    "en": {
      "titulo": "Aggregate Functions",
      "descricao": "Count records, sum values, calculate averages, and find minimums and maximums with COUNT, SUM, AVG, MIN, and MAX."
    },
    "es": {
      "titulo": "Funciones de Agregación",
      "descricao": "Cuenta registros, suma valores, calcula promedios y encuentra mínimos y máximos con COUNT, SUM, AVG, MIN y MAX."
    }
  },
  "etapas": [
    {
      "ordem": 1,
      "tipo": "intro",
      "temAnuncio": false,
      "xpReward": 0,
      "titulo": "Funções de Agregação",
      "conteudo": {
        "emoji": "📈",
        "subtitulo": "Transforme linhas em resumos numéricos poderosos"
      },
      "traducoes": {
        "en": {
          "titulo": "Aggregate Functions",
          "conteudo": {
            "subtitulo": "Transform rows into powerful numeric summaries"
          }
        },
        "es": {
          "titulo": "Funciones de Agregación",
          "conteudo": {
            "subtitulo": "Transforma filas en poderosos resúmenes numéricos"
          }
        }
      }
    },
    {
      "ordem": 2,
      "tipo": "texto",
      "temAnuncio": false,
      "xpReward": 50,
      "titulo": "Inteligência de Dados: COUNT, SUM e AVG",
      "conteudo": {
        "blocos": [
          "Até agora, você aprendeu a buscar linhas individuais e a unir mundos diferentes. Mas no **Neon.tech**, o verdadeiro poder de um Arquiteto de Dados surge ao transformar milhares de linhas em um único número estratégico. Para isso, usamos as **Funções de Agregação**.",
          "Essas funções processam um conjunto de valores e retornam um único resultado resumido. Elas são a base de qualquer relatório de inteligência.",
          {
            "type": "definicao",
            "termo": "Funções de Agregação",
            "def": "Comandos que realizam cálculos em várias linhas de uma coluna para retornar um valor único."
          },
          "Aqui estão as três ferramentas fundamentais:",
          "* **COUNT:** Conta o número total de linhas ou registros.",
          "* **SUM:** Soma todos os valores numéricos de uma coluna.",
          "* **AVG:** Calcula a média aritmética (soma dividida pela quantidade).",
          "**Analogia do Censo Galáctico:** Imagine que você está realizando um censo em uma galáxia. O **COUNT** diz quantos cidadãos existem. O **SUM** revela quanta energia todos eles consomem juntos. E o **AVG** (Average) informa qual é o consumo médio de energia por pessoa. São perspectivas diferentes sobre a mesma massa de dados.",
          {
            "type": "code",
            "code": "SELECT \n  COUNT(*) AS total_naves, \n  SUM(tripulantes) AS total_pessoas,\n  AVG(tripulantes) AS media_por_nave\nFROM naves;",
            "lese": "Conte as naves, some o total de tripulantes e calcule a média de tripulação por nave."
          }
        ]
      },
      "traducoes": {
        "en": {
          "titulo": "Data Intelligence: COUNT, SUM, and AVG",
          "conteudo": {
            "blocos": [
              "So far, you've learned to fetch individual rows. In **Neon.tech**, real power comes from turning thousands of rows into a single strategic number using **Aggregate Functions**.",
              "These functions process a set of values and return a single summarized result.",
              "**Galactic Census Analogy:** Imagine a galaxy-wide census. **COUNT** tells you how many citizens exist. **SUM** reveals how much energy they all consume together. **AVG** gives the average consumption per person."
            ]
          }
        },
        "es": {
          "titulo": "Inteligencia de Datos: COUNT, SUM y AVG",
          "conteudo": {
            "blocos": [
              "Hasta ahora, has aprendido a buscar filas individuales. En **Neon.tech**, el verdadero poder surge al transformar miles de filas en un único número estratégico usando **Funciones de Agregación**.",
              "Estas funciones procesan un conjunto de valores y devuelven un único resultado resumido.",
              "**Analogía del Censo Galáctico:** Imagina un censo en una galaxia. **COUNT** dice cuántos ciudadanos existen. **SUM** revela cuánta energía consumen todos juntos. **AVG** informa el consumo promedio por persona."
            ]
          }
        }
      }
    },
    {
      "ordem": 3,
      "tipo": "exercicio",
      "temAnuncio": false,
      "xpReward": 100,
      "titulo": "Calculando o Tesouro",
      "conteudo": {
        "modo": "quiz",
        "quizTipo": "multipla",
        "instrucao": "Qual função de agregação deve ser utilizada se você quiser saber a soma total de créditos em uma tabela de transações bancárias?",
        "opcoes": [
          "COUNT",
          "SUM",
          "AVG",
          "TOTAL"
        ],
        "indiceCorreto": 1,
        "dica": "Dica de Ouro: Pense na operação matemática de adição. Qual nome em inglês representa o total somado?"
      },
      "traducoes": {
        "en": {
          "titulo": "Calculating the Treasure",
          "conteudo": {
            "modo": "quiz",
            "quizTipo": "multipla",
            "instrucao": "Which aggregate function should be used if you want to know the total sum of credits in a bank transaction table?",
            "opcoes": [
              "COUNT",
              "SUM",
              "AVG",
              "TOTAL"
            ],
            "indiceCorreto": 1
          }
        },
        "es": {
          "titulo": "Calculando el Tesoro",
          "conteudo": {
            "modo": "quiz",
            "quizTipo": "multipla",
            "instrucao": "¿Qué función de agregação debe utilizarse si quieres saber la suma total de créditos en una tabla de transacciones bancarias?",
            "opcoes": [
              "COUNT",
              "SUM",
              "AVG",
              "TOTAL"
            ],
            "indiceCorreto": 1
          }
        }
      }
    },
    {
      "ordem": 4,
      "tipo": "exercicio",
      "temAnuncio": false,
      "xpReward": 100,
      "titulo": "V ou F: O Alcance do Asterisco",
      "conteudo": {
        "modo": "quiz",
        "quizTipo": "vf",
        "instrucao": "Sobre o comportamento da função de contagem:",
        "afirmacao": "A função COUNT(*) conta todas as linhas presentes na tabela, incluindo aquelas que possuem valores nulos (NULL) em suas colunas.",
        "respostaCorreta": true,
        "dica": "Dica de Ouro: O asterisco (*) indica ao banco que ele deve olhar para a linha como um todo, não para uma coluna específica."
      },
      "traducoes": {
        "en": {
          "titulo": "T/F: The Asterisk Reach",
          "conteudo": {
            "modo": "quiz",
            "quizTipo": "vf",
            "instrucao": "About the count function behavior:",
            "afirmacao": "The COUNT(*) function counts all rows present in the table, including those that have null values (NULL) in their columns.",
            "respostaCorreta": true
          }
        },
        "es": {
          "titulo": "V o F: El Alcance del Asterisco",
          "conteudo": {
            "modo": "quiz",
            "quizTipo": "vf",
            "instrucao": "Sobre el comportamiento de la función de conteo:",
            "afirmacao": "La función COUNT(*) cuenta todas las filas presentes en la tabla, incluyendo aquellas que poseen valores nulos (NULL) en sus columnas.",
            "respostaCorreta": true
          }
        }
      }
    },
    {
      "ordem": 5,
      "tipo": "exercicio",
      "temAnuncio": true,
      "xpReward": 100,
      "titulo": "Mão na Massa: Média Populacional",
      "conteudo": {
        "modo": "sql",
        "instrucao": "Calcule a média (AVG) da população da tabela 'planetas'. Nomeie a coluna de resultado como 'media_populacao'.",
        "placeholder": "SELECT ... FROM planetas;",
        "schema": "CREATE TABLE planetas (id SERIAL PRIMARY KEY, nome TEXT, populacao INT); INSERT INTO planetas (nome, populacao) VALUES ('Terra', 7000), ('Marte', 500), ('Vênus', 0);",
        "checkType": "columns",
        "checkConfig": {
          "required_columns": [
            "media_populacao"
          ],
          "aggregate_function": "AVG"
        },
        "dica": "Dica de Ouro: Use a sintaxe SELECT FUNCÃO(coluna) AS apelido FROM tabela. A função de média é o AVG.",
        "explicacaoTecnica": "A função AVG soma os valores da coluna populacao e divide pelo número de registros encontrados, gerando um resultado do tipo float/numeric."
      },
      "traducoes": {
        "en": {
          "titulo": "Hands-on: Population Average",
          "conteudo": {
            "instrucao": "Calculate the average (AVG) population of the 'planetas' table. Name the result column as 'media_populacao'.",
            "dica": "Remember to use 'AS media_populacao' to rename the calculation output column."
          }
        },
        "es": {
          "titulo": "Manos a la obra: Promedio Poblacional",
          "conteudo": {
            "instrucao": "Calcula el promedio (AVG) de la población de la tabla 'planetas'. Nombra a la columna de resultado como 'media_populacao'.",
            "dica": "Recuerda usar 'AS media_populacao' para renombrar la columna de salida del cálculo."
          }
        }
      }
    },
    {
      "ordem": 6,
      "tipo": "texto",
      "temAnuncio": false,
      "xpReward": 50,
      "titulo": "Organizando a Galaxia: O Comando GROUP BY",
      "conteudo": {
        "blocos": [
          "Você já sabe como resumir toda uma tabela em um único número. Mas e se você precisasse saber o total de naves **para cada planeta** separadamente? No **Neon.tech**, usamos o **GROUP BY** para fatiar nossos dados em categorias.",
          "O GROUP BY divide as linhas da tabela em grupos com base nos valores de uma ou mais colunas. Depois de criar esses grupos, o SQL aplica a função de agregação (como COUNT ou SUM) em cada um deles de forma individual.",
          {
            "type": "definicao",
            "termo": "Regra de Ouro",
            "def": "Todas as colunas que aparecem no SELECT e não possuem uma função de agregação devem, obrigatoriamente, estar listadas na cláusula GROUP BY."
          },
          "**Analogia das Moedas:** Imagine que você tem uma sacola cheia de moedas de vários países. Para saber quanto tem de cada uma, primeiro você as **agrupa** em pilhas (Brasil, EUA, Japão). Só depois de estarem separadas é que você as conta (COUNT) ou soma os valores (SUM) de cada pilha individualmente.",
          "Sem o agrupamento, o SQL tentaria contar tudo junto. Com ele, você gera um relatório detalhado por categoria.",
          {
            "type": "code",
            "code": "SELECT planeta_id, COUNT(*) \nFROM naves \nGROUP BY planeta_id;",
            "lese": "Selecione o ID do planeta e conte as naves, agrupando os resultados para que cada planeta apareça em uma linha com seu respectivo total."
          }
        ]
      },
      "traducoes": {
        "en": {
          "titulo": "Organizing the Galaxy: The GROUP BY Command",
          "conteudo": {
            "blocos": [
              "You already know how to summarize a whole table into a single number. But what if you needed to know the total of ships **for each planet** separately? In **Neon.tech**, we use **GROUP BY** to slice our data into categories.",
              "GROUP BY divides table rows into groups based on values. After creating these groups, SQL applies the aggregate function (like COUNT or SUM) to each one individually.",
              "**Coin Analogy:** Imagine you have a bag of coins from different countries. To find out how much you have of each, you first **group** them into piles (Brazil, USA, Japan). Only then do you count (COUNT) or sum (SUM) each pile."
            ]
          }
        },
        "es": {
          "titulo": "Organizando la Galaxia: El Comando GROUP BY",
          "conteudo": {
            "blocos": [
              "Ya sabes resumir toda una tabla en un solo número. ¿Pero qué pasa si necesitas saber el total de naves **por cada planeta** por separado? En **Neon.tech**, usamos **GROUP BY** para segmentar nuestros datos en categorías.",
              "GROUP BY divide las filas de la tabla en grupos basados en valores. Después de crear estos grupos, SQL aplica la función de agregación (como COUNT o SUM) a cada uno individualmente.",
              "**Analogía de las Monedas:** Imagina que tienes una bolsa de monedas de varios países. Para saber cuánto tienes de cada una, primero las **agrupas** en montones (Brasil, EE.UU., Japón). Solo después las cuentas (COUNT) o sumas (SUM) por separado."
            ]
          }
        }
      }
    },
    {
      "ordem": 7,
      "tipo": "exercicio",
      "temAnuncio": false,
      "xpReward": 100,
      "titulo": "Fatiando os Resultados",
      "conteudo": {
        "modo": "quiz",
        "quizTipo": "multipla",
        "instrucao": "Qual cláusula SQL deve ser usada para agrupar as linhas que possuem valores idênticos em colunas específicas, permitindo realizar cálculos por categoria?",
        "opcoes": [
          "ORDER BY",
          "WHERE",
          "GROUP BY",
          "HAVING"
        ],
        "indiceCorreto": 2,
        "dica": "Dica de Ouro: Pense no comando que separa os dados em 'caixas' antes de realizar o cálculo."
      },
      "traducoes": {
        "en": {
          "titulo": "Slicing Results",
          "conteudo": {
            "modo": "quiz",
            "quizTipo": "multipla",
            "instrucao": "Which SQL clause should be used to group rows that have identical values in specific columns, allowing calculations by category?",
            "opcoes": [
              "ORDER BY",
              "WHERE",
              "GROUP BY",
              "HAVING"
            ],
            "indiceCorreto": 2
          }
        },
        "es": {
          "titulo": "Segmentando Resultados",
          "conteudo": {
            "modo": "quiz",
            "quizTipo": "multipla",
            "instrucao": "¿Qué cláusula SQL debe usarse para agrupar las filas que poseen valores idénticos en columnas específicas, permitiendo realizar cálculos por categoría?",
            "opcoes": [
              "ORDER BY",
              "WHERE",
              "GROUP BY",
              "HAVING"
            ],
            "indiceCorreto": 2
          }
        }
      }
    },
    {
      "ordem": 8,
      "tipo": "exercicio",
      "temAnuncio": false,
      "xpReward": 100,
      "titulo": "V ou F: A Exigência do Grupo",
      "conteudo": {
        "modo": "quiz",
        "quizTipo": "vf",
        "instrucao": "Sobre as regras de sintaxe do agrupamento:",
        "afirmacao": "Ao usar o comando GROUP BY, é perfeitamente possível exibir o nome de uma coluna individual no SELECT sem que ela esteja presente na cláusula de agrupamento ou dentro de uma função.",
        "respostaCorreta": false,
        "dica": "Dica de Ouro: Lembre-se da Regra de Ouro: se a coluna está 'sozinha' no SELECT, ela deve estar no agrupamento."
      },
      "traducoes": {
        "en": {
          "titulo": "T/F: The Group Requirement",
          "conteudo": {
            "modo": "quiz",
            "quizTipo": "vf",
            "instrucao": "About grouping syntax rules:",
            "afirmacao": "When using the GROUP BY command, it is perfectly possible to display an individual column name in the SELECT without it being present in the grouping clause or inside a function.",
            "respostaCorreta": false
          }
        },
        "es": {
          "titulo": "V o F: La Exigencia del Grupo",
          "conteudo": {
            "modo": "quiz",
            "quizTipo": "vf",
            "instrucao": "Sobre las reglas de sintaxis del agrupamiento:",
            "afirmacao": "Al usar el comando GROUP BY, es perfectamente posible mostrar el nombre de una columna individual en el SELECT sin que esté presente en la cláusula de agrupamiento o dentro de una función.",
            "respostaCorreta": false
          }
        }
      }
    },
    {
      "ordem": 9,
      "tipo": "exercicio",
      "temAnuncio": true,
      "xpReward": 100,
      "titulo": "Mão na Massa: Censo de Naves",
      "conteudo": {
        "modo": "sql",
        "instrucao": "Conte quantas naves existem para cada planeta_id. O resultado deve exibir as colunas planeta_id e a contagem com o nome total_naves.",
        "placeholder": "SELECT ..., COUNT(*) AS total_naves FROM ... GROUP BY ...;",
        "schema": "CREATE TABLE naves (id SERIAL PRIMARY KEY, nome TEXT, planeta_id INT); INSERT INTO naves (nome, planeta_id) VALUES ('Explorer', 1), ('Voyager', 1), ('Falcon', 2);",
        "checkType": "columns",
        "checkConfig": {
          "required_columns": [
            "planeta_id",
            "total_naves"
          ],
          "group_by_column": "planeta_id"
        },
        "dica": "Dica de Ouro: A estrutura é SELECT coluna, COUNT(*) AS apelido FROM tabela GROUP BY coluna.",
        "explicacaoTecnica": "O GROUP BY aglutina as linhas com o mesmo planeta_id, permitindo que o COUNT(*) calcule o total de ocorrências dentro de cada balde (bucket) de ID."
      },
      "traducoes": {
        "en": {
          "titulo": "Hands-on: Ship Census",
          "conteudo": {
            "instrucao": "Count how many ships exist for each planeta_id. The result should display the columns planeta_id and the count named total_naves.",
            "dica": "Use SELECT planeta_id, COUNT(*) AS total_naves and remember to group by the planeta_id column at the end."
          }
        },
        "es": {
          "titulo": "Manos a la obra: Censo de Naves",
          "conteudo": {
            "instrucao": "Cuenta cuántas naves existen por cada planeta_id. El resultado debe mostrar las columnas planeta_id y el conteo con el nombre total_naves.",
            "dica": "Usa SELECT planeta_id, COUNT(*) AS total_naves y recuerda agrupar por la columna planeta_id al final."
          }
        }
      }
    },
    {
      "ordem": 10,
      "tipo": "texto",
      "temAnuncio": false,
      "xpReward": 50,
      "titulo": "O Filtro dos Grupos: O Comando HAVING",
      "conteudo": {
        "blocos": [
          "Você já aprendeu a fatiar a galaxia em grupos com o **GROUP BY**. Mas e se você precisasse de um relatório que mostrasse apenas os grupos que atingiram uma meta específica? Por exemplo: 'Quais planetas possuem mais de 5 naves?'. Para filtrar cálculos, o WHERE não é suficiente; você precisa do **HAVING**.",
          "A cláusula **HAVING** é o filtro que atua sobre os resultados das funções de agregação. Enquanto o WHERE olha para as linhas antes de serem processadas, o HAVING olha para os totais depois que o agrupamento foi feito.",
          {
            "type": "definicao",
            "termo": "Diferença Vital",
            "def": "WHERE filtra linhas individuais (input). HAVING filtra grupos calculados (output)."
          },
          "**Analogia do Torneio Intergaláctico:** Imagine a organização de um torneio. Primeiro, você agrupa os atletas por planeta. O **WHERE** seria usado para eliminar atletas individuais (ex: 'onde idade > 18'). O **HAVING**, por outro lado, eliminaria delegações inteiras (ex: 'tendo mais de 10 atletas'). Se um planeta trouxe apenas 2 atletas, o grupo todo é descartado pelo HAVING.",
          "No **Neon.tech**, entender essa distinção é a chave para criar painéis de controle e relatórios analíticos de alta precisão.",
          {
            "type": "code",
            "code": "SELECT planeta_id, COUNT(*) \nFROM naves \nGROUP BY planeta_id \nHAVING COUNT(*) > 5;",
            "lese": "Agrupe as naves por planeta e conte-as, mas exiba apenas os planetas cujo total de naves seja estritamente maior que 5."
          }
        ]
      },
      "traducoes": {
        "en": {
          "titulo": "Filtering Groups: The HAVING Command",
          "conteudo": {
            "blocos": [
              "You've learned to slice the galaxy into groups. But what if you need a report showing only groups that met a goal? For example: 'Which planets have more than 5 ships?'. To filter calculations, WHERE isn't enough; you need **HAVING**.",
              "The **HAVING** clause is the filter for aggregate function results. While WHERE looks at rows before they are processed, HAVING looks at totals after grouping.",
              "**Intergalactic Tournament Analogy:** Imagine a tournament. First, you group athletes by planet. **WHERE** filters individual athletes. **HAVING** filters entire delegations based on their size."
            ]
          }
        },
        "es": {
          "titulo": "El Filtro de los Grupos: El Comando HAVING",
          "conteudo": {
            "blocos": [
              "Ya aprendiste a segmentar la galaxia en grupos. ¿Pero qué pasa si necesitas un informe que muestre solo los grupos que alcanzaron una meta? Por ejemplo: '¿Qué planetas tienen más de 5 naves?'. Para filtrar cálculos, WHERE no es suficiente; necesitas **HAVING**.",
              "La cláusula **HAVING** es el filtro que actúa sobre los resultados de las funciones de agregación. Mientras WHERE mira las filas antes de ser procesadas, HAVING mira los totales después del agrupamiento.",
              "**Analogía del Torneo Intergaláctico:** Imagina un torneo. Primero, agrupas a los atletas por planeta. **WHERE** filtra atletas individuales. **HAVING** filtra delegaciones enteras basadas en su tamaño total."
            ]
          }
        }
      }
    },
    {
      "ordem": 11,
      "tipo": "exercicio",
      "temAnuncio": false,
      "xpReward": 100,
      "titulo": "Filtrando Agregados",
      "conteudo": {
        "modo": "quiz",
        "quizTipo": "multipla",
        "instrucao": "Qual cláusula SQL deve ser obrigatoriamente usada para filtrar resultados baseados em uma função de agregação, como COUNT, SUM ou AVG?",
        "opcoes": [
          "WHERE",
          "ORDER BY",
          "GROUP BY",
          "HAVING"
        ],
        "indiceCorreto": 3,
        "dica": "Dica de Ouro: O WHERE age no registro individual. Qual cláusula age no resultado final do grupo?"
      },
      "traducoes": {
        "en": {
          "titulo": "Filtering Aggregates",
          "conteudo": {
            "modo": "quiz",
            "quizTipo": "multipla",
            "instrucao": "Which SQL clause must be used to filter results based on an aggregate function like COUNT, SUM, or AVG?",
            "opcoes": [
              "WHERE",
              "ORDER BY",
              "GROUP BY",
              "HAVING"
            ],
            "indiceCorreto": 3
          }
        },
        "es": {
          "titulo": "Filtrando Agregados",
          "conteudo": {
            "modo": "quiz",
            "quizTipo": "multipla",
            "instrucao": "¿Qué cláusula SQL debe usarse obligatoriamente para filtrar resultados basados en una función de agregación, como COUNT, SUM o AVG?",
            "opcoes": [
              "WHERE",
              "ORDER BY",
              "GROUP BY",
              "HAVING"
            ],
            "indiceCorreto": 3
          }
        }
      }
    },
    {
      "ordem": 12,
      "tipo": "exercicio",
      "temAnuncio": false,
      "xpReward": 100,
      "titulo": "V ou F: A Troca Impossível",
      "conteudo": {
        "modo": "quiz",
        "quizTipo": "vf",
        "instrucao": "Sobre a lógica de filtragem do banco de dados:",
        "afirmacao": "É possível substituir completamente a cláusula HAVING pela cláusula WHERE para filtrar a soma de uma coluna agrupada (ex: WHERE SUM(valor) > 100).",
        "respostaCorreta": false,
        "dica": "Dica de Ouro: O SQL tem uma ordem de execução rígida: as linhas são filtradas (WHERE) antes de serem contadas."
      },
      "traducoes": {
        "en": {
          "titulo": "T/F: The Impossible Swap",
          "conteudo": {
            "modo": "quiz",
            "quizTipo": "vf",
            "instrucao": "About database filtering logic:",
            "afirmacao": "It is possible to completely replace the HAVING clause with the WHERE clause to filter the sum of a grouped column (e.g., WHERE SUM(valor) > 100).",
            "respostaCorreta": false
          }
        },
        "es": {
          "titulo": "V o F: El Intercambio Imposible",
          "conteudo": {
            "modo": "quiz",
            "quizTipo": "vf",
            "instrucao": "Sobre la lógica de filtrado de la base de datos:",
            "afirmacao": "Es posible sustituir completamente la cláusula HAVING por la cláusula WHERE para filtrar la suma de una columna agrupada (ej: WHERE SUM(valor) > 100).",
            "respostaCorreta": false
          }
        }
      }
    },
    {
      "ordem": 13,
      "tipo": "exercicio",
      "temAnuncio": true,
      "xpReward": 100,
      "titulo": "Mão na Massa: Planetas Populosos",
      "conteudo": {
        "modo": "sql",
        "instrucao": "Selecione o planeta_id e a contagem de naves. Mostre apenas os IDs de planetas que possuem mais de 1 nave cadastrada.",
        "placeholder": "SELECT planeta_id, COUNT(*) FROM naves ...",
        "schema": "CREATE TABLE naves (id SERIAL PRIMARY KEY, nome TEXT, planeta_id INT); INSERT INTO naves (nome, planeta_id) VALUES ('Titan', 1), ('Ares', 1), ('Luna', 2);",
        "checkType": "columns",
        "checkConfig": {
          "required_columns": [
            "planeta_id",
            "count"
          ],
          "having_clause": "COUNT(*) > 1"
        },
        "dica": "Dica de Ouro: Sua query deve seguir a ordem: SELECT -> FROM -> GROUP BY -> HAVING.",
        "explicacaoTecnica": "O PostgreSQL primeiro agrupa os registros por ID, conta quantos existem em cada grupo e, por fim, remove do resultado os grupos que não atendem à condição do HAVING."
      },
      "traducoes": {
        "en": {
          "titulo": "Hands-on: Populated Planets",
          "conteudo": {
            "instrucao": "Select the planeta_id and the ship count. Show only the planet IDs that have more than 1 ship registered.",
            "dica": "Remember to group by planeta_id before applying the HAVING filter."
          }
        },
        "es": {
          "titulo": "Manos a la obra: Planetas Poblados",
          "conteudo": {
            "instrucao": "Selecciona el planeta_id y el conteo de naves. Muestra solo los IDs de planetas que tienen más de 1 nave registrada.",
            "dica": "Recuerda agrupar por planeta_id antes de aplicar el filtro HAVING."
          }
        }
      }
    },
    {
      "ordem": 14,
      "tipo": "texto",
      "temAnuncio": false,
      "xpReward": 50,
      "titulo": "O Filtro dos Grupos: Cláusula HAVING",
      "conteudo": {
        "blocos": [
          "Imagine que você tenta usar o WHERE para filtrar o resultado de uma contagem: `WHERE COUNT(*) > 1`. O PostgreSQL irá reclamar imediatamente. Por quê? Porque o **WHERE filtra linhas individuais** antes mesmo do banco saber o que é um grupo.",
          "A cláusula **HAVING** é a solução para esse dilema. Ela funciona como um filtro de segurança exclusivo para os grupos já formados pelo GROUP BY.",
          {
            "type": "definicao",
            "termo": "HAVING",
            "def": "Cláusula utilizada para filtrar os resultados de funções de agregação (como COUNT, SUM, AVG) após o agrupamento dos dados."
          },
          "**Analogia da Sala VIP:** Primeiro, o bouncer (GROUP BY) separa as pessoas em grupos por categoria (ex: Clientes Ouro, Prata e Bronze). Depois, o **HAVING** entra em cena para escolher apenas os grupos que possuem mais de X pessoas para entrar na Sala VIP.",
          "**Como se lê:** 'Selecione o clima e a contagem, agrupe por clima, mas mantenha apenas (**HAVING**) aqueles onde a contagem final for maior que 1'.",
          {
            "type": "code",
            "code": "SELECT clima, COUNT(*) \nFROM planetas \nGROUP BY clima \nHAVING COUNT(*) > 1;",
            "lese": "Agrupe os planetas por clima e conte-os, mas mostre apenas as linhas de clima que resultaram em mais de um planeta."
          }
        ]
      },
      "traducoes": {
        "en": {
          "titulo": "The Group Filter: HAVING Clause",
          "conteudo": {
            "blocos": [
              "Imagine trying to use WHERE to filter a count result: `WHERE COUNT(*) > 1`. PostgreSQL will complain immediately. Why? Because **WHERE filters individual rows** before the database even knows what a group is.",
              "The **HAVING** clause is the solution to this dilemma. It works like an exclusive security filter for groups already formed by GROUP BY.",
              {
                "type": "definicao",
                "termo": "HAVING",
                "def": "A clause used to filter the results of aggregate functions (like COUNT, SUM, AVG) after the data has been grouped."
              },
              "**VIP Room Analogy:** First, the bouncer (GROUP BY) sorts people into groups by category (e.g. Gold, Silver, Bronze). Then **HAVING** steps in to choose only groups with more than X people for VIP access.",
              "**How to read it:** 'Select the climate and the count, group by climate, but keep only (**HAVING**) those where the final count is greater than 1.'",
              {
                "type": "code",
                "code": "SELECT clima, COUNT(*) \nFROM planetas \nGROUP BY clima \nHAVING COUNT(*) > 1;",
                "lese": "Group planets by climate and count them, but show only climate rows where more than one planet matched."
              }
            ]
          }
        },
        "es": {
          "titulo": "El Filtro de Grupos: Cláusula HAVING",
          "conteudo": {
            "blocos": [
              "Imagina intentar usar WHERE para filtrar el resultado de un conteo: `WHERE COUNT(*) > 1`. PostgreSQL se quejará al instante. ¿Por qué? Porque **WHERE filtra filas individuales** antes de que la base sepa qué es un grupo.",
              "La cláusula **HAVING** es la solución a ese dilema. Funciona como un filtro de seguridad exclusivo para los grupos ya formados por GROUP BY.",
              {
                "type": "definicao",
                "termo": "HAVING",
                "def": "Cláusula utilizada para filtrar los resultados de funciones de agregación (como COUNT, SUM, AVG) después del agrupamiento de los datos."
              },
              "**Analogía de la Sala VIP:** Primero, el portero (GROUP BY) separa a las personas en grupos por categoría (ej.: Oro, Plata y Bronce). Después, el **HAVING** elige solo los grupos que tienen más de X personas para entrar en la Sala VIP.",
              "**Cómo se lee:** 'Selecciona el clima y el conteo, agrupa por clima, pero conserva solo (**HAVING**) aquellos donde el conteo final sea mayor que 1'.",
              {
                "type": "code",
                "code": "SELECT clima, COUNT(*) \nFROM planetas \nGROUP BY clima \nHAVING COUNT(*) > 1;",
                "lese": "Agrupa los planetas por clima y cuéntalos, pero muestra solo las filas de clima con más de un planeta."
              }
            ]
          }
        }
      }
    },
    {
      "ordem": 15,
      "tipo": "exercicio",
      "temAnuncio": false,
      "xpReward": 100,
      "titulo": "WHERE vs HAVING",
      "conteudo": {
        "modo": "quiz",
        "quizTipo": "multipla",
        "instrucao": "Qual é a principal diferença técnica entre a utilização das cláusulas WHERE e HAVING em uma consulta SQL?",
        "opcoes": [
          "O WHERE é usado apenas para números e o HAVING apenas para textos.",
          "O WHERE filtra registros individuais antes da agregação; o HAVING filtra grupos após a agregação.",
          "O HAVING é opcional, enquanto o WHERE é obrigatório em todas as consultas.",
          "Não há diferença; ambas servem exatamente para o mesmo propósito de filtragem."
        ],
        "indiceCorreto": 1,
        "dica": "O WHERE age no registro individual. O HAVING age no resultado do cálculo do grupo.",
        "dicas": [
          "O WHERE age no registro individual.",
          "O HAVING age no resultado do cálculo do grupo.",
          "O HAVING age no resultado do cálculo do grupo."
        ]
      },
      "traducoes": {
        "en": {
          "titulo": "WHERE vs HAVING",
          "conteudo": {
            "modo": "quiz",
            "quizTipo": "multipla",
            "instrucao": "What is the main technical difference between using WHERE and HAVING clauses in an SQL query?",
            "opcoes": [
              "WHERE is used only for numbers and HAVING only for text.",
              "WHERE filters individual records before aggregation; HAVING filters groups after aggregation.",
              "HAVING is optional, while WHERE is mandatory in all queries.",
              "There is no difference; both serve exactly the same filtering purpose."
            ],
            "indiceCorreto": 1,
            "dica": "WHERE acts on individual records. HAVING acts on the group calculation result.",
            "dicas": [
              "WHERE acts on individual records.",
              "HAVING acts on the group calculation result.",
              "HAVING acts on the group calculation result."
            ]
          }
        },
        "es": {
          "titulo": "WHERE vs HAVING",
          "conteudo": {
            "modo": "quiz",
            "quizTipo": "multipla",
            "instrucao": "¿Cuál es la principal diferencia técnica entre el uso de las cláusulas WHERE y HAVING en una consulta SQL?",
            "opcoes": [
              "El WHERE se usa solo para números y el HAVING solo para textos.",
              "El WHERE filtra registros individuales antes de la agregación; el HAVING filtra grupos después de la agregación.",
              "El HAVING es opcional, mientras que el WHERE es obligatorio en todas las consultas.",
              "No hay diferencia; ambas sirven exactamente para el mismo propósito de filtrado."
            ],
            "indiceCorreto": 1,
            "dica": "El WHERE actúa en el registro individual. El HAVING actúa en el resultado del cálculo del grupo.",
            "dicas": [
              "El WHERE actúa en el registro individual.",
              "El HAVING actúa en el resultado del cálculo del grupo.",
              "El HAVING actúa en el resultado del cálculo del grupo."
            ]
          }
        }
      }
    },
    {
      "ordem": 16,
      "tipo": "exercicio",
      "temAnuncio": false,
      "xpReward": 100,
      "titulo": "Dependência de Cláusula",
      "conteudo": {
        "modo": "quiz",
        "quizTipo": "vf",
        "instrucao": "Analise a estrutura lógica do SQL:",
        "afirmacao": "No PostgreSQL, é perfeitamente possível e comum utilizar a cláusula HAVING para realizar filtros sem a necessidade de um GROUP BY na consulta.",
        "respostaCorreta": false,
        "dica": "Sem um grupo formado (GROUP BY), não há 'casa' para o HAVING morar no SQL padrão.",
        "dicas": [
          "Sem um grupo formado (GROUP BY)",
          "não há 'casa' para o HAVING morar no SQL padrão.",
          "Sem um grupo formado (GROUP BY), não há 'casa' para o HAVING morar no SQL padrão."
        ]
      },
      "traducoes": {
        "en": {
          "titulo": "Clause Dependency",
          "conteudo": {
            "modo": "quiz",
            "quizTipo": "vf",
            "instrucao": "Analyze the SQL logical structure:",
            "afirmacao": "In PostgreSQL, it is perfectly possible and common to use the HAVING clause to perform filters without needing a GROUP BY in the query.",
            "respostaCorreta": false,
            "dica": "Without a formed group (GROUP BY), there's no 'home' for HAVING to live in standard SQL.",
            "dicas": [
              "Without a formed group (GROUP BY)",
              "there's no 'home' for HAVING to live in standard SQL.",
              "Without a formed group (GROUP BY), there's no 'home' for HAVING to live in standard SQL."
            ]
          }
        },
        "es": {
          "titulo": "Dependencia de Cláusula",
          "conteudo": {
            "modo": "quiz",
            "quizTipo": "vf",
            "instrucao": "Analiza la estructura lógica de SQL:",
            "afirmacao": "En PostgreSQL, es perfectamente posible y común utilizar la cláusula HAVING para realizar filtros sin necesidad de un GROUP BY en la consulta.",
            "respostaCorreta": false,
            "dica": "Sin un grupo formado (GROUP BY), no hay 'hogar' para que el HAVING resida en el SQL estándar.",
            "dicas": [
              "Sin un grupo formado (GROUP BY)",
              "no hay 'hogar' para que el HAVING resida en el SQL estándar.",
              "Sin un grupo formado (GROUP BY), no hay 'hogar' para que el HAVING resida en el SQL estándar."
            ]
          }
        }
      }
    },
    {
      "ordem": 17,
      "tipo": "exercicio",
      "temAnuncio": true,
      "xpReward": 100,
      "titulo": "Prática: Filtrando Categorias",
      "conteudo": {
        "instrucao": "Selecione o clima e a contagem de planetas, mas mostre apenas os climas que possuem mais de 1 planeta cadastrado.",
        "placeholder": "SELECT ..., COUNT(*) FROM ... GROUP BY ... HAVING ...",
        "schema": "CREATE TABLE planetas (id SERIAL PRIMARY KEY, nome TEXT, clima TEXT); INSERT INTO planetas (nome, clima) VALUES ('Terra', 'Temperado'), ('Marte', 'Árido'), ('Júpiter', 'Gasoso'), ('Kepler-186f', 'Temperado'), ('Vênus', 'Árido');",
        "checkType": "columns",
        "checkConfig": {
          "required_columns": [
            "clima",
            "count"
          ],
          "min_rows": 2
        },
        "dica": "Sua query deve ter a estrutura: SELECT... GROUP BY... HAVING COUNT(*) > 1;",
        "explicacaoTecnica": "O PostgreSQL primeiro agrupa os dados por clima, calcula o COUNT para cada grupo e, por último, aplica a restrição do HAVING para descartar grupos que não atingiram a contagem mínima.",
        "dicas": [
          "Sua query deve ter a estrutura: SELECT...",
          "GROUP BY...",
          "HAVING COUNT(*) > 1;."
        ]
      },
      "traducoes": {
        "en": {
          "titulo": "Practice: Filtering Categories",
          "conteudo": {
            "instrucao": "Select the climate and the planet count, but show only the climates that have more than 1 planet registered.",
            "placeholder": "SELECT ..., COUNT(*) FROM ... GROUP BY ... HAVING ...",
            "schema": "CREATE TABLE planetas (id SERIAL PRIMARY KEY, nome TEXT, clima TEXT); INSERT INTO planetas (nome, clima) VALUES ('Terra', 'Temperado'), ('Marte', 'Árido'), ('Júpiter', 'Gasoso'), ('Kepler-186f', 'Temperado'), ('Vênus', 'Árido');",
            "checkType": "columns",
            "checkConfig": {
              "required_columns": [
                "clima",
                "count"
              ],
              "min_rows": 2
            },
            "dica": "Your query should follow the structure: SELECT... GROUP BY... HAVING COUNT(*) > 1;",
            "explicacaoTecnica": "PostgreSQL first groups data by climate, calculates the COUNT for each group, and finally applies the HAVING constraint to discard groups that didn't reach the minimum count.",
            "dicas": [
              "Your query should follow the structure: SELECT...",
              "GROUP BY...",
              "HAVING COUNT(*) > 1;."
            ]
          }
        },
        "es": {
          "titulo": "Práctica: Filtrando Categorías",
          "conteudo": {
            "instrucao": "Selecciona el clima y el conteo de planetas, pero muestra solo los climas que tienen más de 1 planeta registrado.",
            "placeholder": "SELECT ..., COUNT(*) FROM ... GROUP BY ... HAVING ...",
            "schema": "CREATE TABLE planetas (id SERIAL PRIMARY KEY, nome TEXT, clima TEXT); INSERT INTO planetas (nome, clima) VALUES ('Terra', 'Temperado'), ('Marte', 'Árido'), ('Júpiter', 'Gasoso'), ('Kepler-186f', 'Temperado'), ('Vênus', 'Árido');",
            "checkType": "columns",
            "checkConfig": {
              "required_columns": [
                "clima",
                "count"
              ],
              "min_rows": 2
            },
            "dica": "Tu consulta debe tener la estructura: SELECT... GROUP BY... HAVING COUNT(*) > 1;",
            "explicacaoTecnica": "PostgreSQL primero agrupa los datos por clima, calcula el COUNT para cada grupo y, finalmente, aplica la restricción del HAVING para descartar grupos que no alcanzaron el conteo mínimo.",
            "dicas": [
              "Tu consulta debe tener la estructura: SELECT...",
              "GROUP BY...",
              "HAVING COUNT(*) > 1;."
            ]
          }
        }
      }
    },
    {
      "ordem": 18,
      "tipo": "conclusao",
      "temAnuncio": false,
      "xpReward": 50,
      "titulo": "Agregações dominadas!",
      "conteudo": {
        "mensagem": "Agora você consegue transformar dados brutos em insights numéricos. COUNT, SUM, AVG, MIN e MAX são ferramentas diárias de qualquer analista de dados!",
        "xpGanho": 350
      },
      "traducoes": {
        "en": {
          "titulo": "Aggregations mastered!",
          "conteudo": {
            "mensagem": "Now you can transform raw data into numeric insights. COUNT, SUM, AVG, MIN, and MAX are daily tools for any data analyst!"
          }
        },
        "es": {
          "titulo": "¡Agregaciones dominadas!",
          "conteudo": {
            "mensagem": "¡Ahora puedes transformar datos brutos en insights numéricos. COUNT, SUM, AVG, MIN y MAX son herramientas cotidianas de cualquier analista de datos!"
          }
        }
      }
    }
  ]
}